simobject/__init__.py
simobject/heartbeat_object.py
simobject/quantity.py
simobject/simulation.py
simobject/updater.py
simobject-0.1.5.dist-info/METADATA
simobject-0.1.5.dist-info/RECORD
simobject-0.1.5.dist-info/WHEEL
simobject-0.1.5.dist-info/top_level.txt
simobject-0.1.5.dist-info/zip-safe
