Metadata-Version: 2.1
Name: simobject
Version: 0.1.5
Summary: simple basic framework for a simulation
Home-page: https://github.com/birnstiel/simobject
Author: Til Birnstiel
Author-email: til.birnstiel@lmu.de
License: GPLv3
Platform: UNKNOWN
Requires-Dist: pytest
Requires-Dist: numpy
